generic-crawler/__init__.py
generic-crawler/webscraper.py
generic_crawler/__init__.py
generic_crawler/webscraper.py
generic_crawler-0.4.0.dist-info/METADATA
generic_crawler-0.4.0.dist-info/WHEEL
generic_crawler-0.4.0.dist-info/top_level.txt
generic_crawler-0.4.0.dist-info/RECORD
