Metadata-Version: 2.1
Name: generic-crawler
Version: 0.4.0
Summary: A simple web scraper for downloading images, tables, and text from a webpage.
Author: Said Mohamed Amine
Author-email: amine8said@gmail.com
Classifier: Development Status :: 3 - Alpha
Classifier: Intended Audience :: Developers
Classifier: License :: OSI Approved :: MIT License
Classifier: Operating System :: OS Independent
Classifier: Programming Language :: Python
Classifier: Programming Language :: Python :: 3
Classifier: Programming Language :: Python :: 3.7
Classifier: Programming Language :: Python :: 3.8
Classifier: Programming Language :: Python :: 3.9
Requires-Python: >=3.7
Requires-Dist: beautifulsoup4
Requires-Dist: lxml
Requires-Dist: pandas
Requires-Dist: requests
Requires-Dist: selenium
Requires-Dist: tqdm
